flowgeo/__init__.py
flowgeo/export/templates/base.html
flowgeo/export/templates/slide_view.html
flowgeo/static/README.md
flowgeo/static/js/plotly-2.26.0.min.js
flowgeo/static/js/polyfill.min.js
flowgeo/static/js/tex-mml-chtml.js
flowgeo-0.2.0.dist-info/licenses/LICENSE
flowgeo-0.2.0.dist-info/METADATA
flowgeo-0.2.0.dist-info/WHEEL
flowgeo-0.2.0.dist-info/top_level.txt
flowgeo-0.2.0.dist-info/RECORD
